Metadata-Version: 1.2
Name: lulzcode
Version: 1.0.10
Summary: LulzCODE – Simple way for good encoding some text.
Home-page: UNKNOWN
Author: LulzLoL231
Author-email: lznet@pm.me
License: UNKNOWN
Project-URL: Source Code, https://github.com/LulzLoL231/lulzcode
Keywords: encode lulz lulzcode
Platform: UNKNOWN
